sales.py
settings.py
junhao_sales-0.0.1.dist-info/METADATA
junhao_sales-0.0.1.dist-info/WHEEL
junhao_sales-0.0.1.dist-info/RECORD
